AUTHORS.rst
CONTRIBUTING.rst
LICENSE
MANIFEST.in
README.md
setup.cfg
setup.py
docs/Makefile
docs/YAKEvsBaselines.jpg
docs/authors.rst
docs/conf.py
docs/contributing.rst
docs/history.rst
docs/index.rst
docs/installation.rst
docs/make.bat
docs/pyake.rst
docs/readme.rst
docs/usage.rst
tests/__init__.py
tests/doc1.txt
tests/test_yake.py
yake/Levenshtein.py
yake/__init__.py
yake/cli.py
yake/datarepresentation.py
yake/yake.py
yake/StopwordsList/stopwords_ar.txt
yake/StopwordsList/stopwords_bg.txt
yake/StopwordsList/stopwords_br.txt
yake/StopwordsList/stopwords_cz.txt
yake/StopwordsList/stopwords_da.txt
yake/StopwordsList/stopwords_de.txt
yake/StopwordsList/stopwords_el.txt
yake/StopwordsList/stopwords_en.txt
yake/StopwordsList/stopwords_es.txt
yake/StopwordsList/stopwords_et.txt
yake/StopwordsList/stopwords_fa.txt
yake/StopwordsList/stopwords_fi.txt
yake/StopwordsList/stopwords_fr.txt
yake/StopwordsList/stopwords_hi.txt
yake/StopwordsList/stopwords_hr.txt
yake/StopwordsList/stopwords_hu.txt
yake/StopwordsList/stopwords_hy.txt
yake/StopwordsList/stopwords_id.txt
yake/StopwordsList/stopwords_it.txt
yake/StopwordsList/stopwords_ja.txt
yake/StopwordsList/stopwords_lt.txt
yake/StopwordsList/stopwords_lv.txt
yake/StopwordsList/stopwords_nl.txt
yake/StopwordsList/stopwords_no.txt
yake/StopwordsList/stopwords_pl.txt
yake/StopwordsList/stopwords_pt.txt
yake/StopwordsList/stopwords_ro.txt
yake/StopwordsList/stopwords_ru.txt
yake/StopwordsList/stopwords_sk.txt
yake/StopwordsList/stopwords_sl.txt
yake/StopwordsList/stopwords_sv.txt
yake/StopwordsList/stopwords_tr.txt
yake/StopwordsList/stopwords_uk.txt
yake/StopwordsList/stopwords_zh.txt
yake_github.egg-info/PKG-INFO
yake_github.egg-info/SOURCES.txt
yake_github.egg-info/dependency_links.txt
yake_github.egg-info/entry_points.txt
yake_github.egg-info/not-zip-safe
yake_github.egg-info/requires.txt
yake_github.egg-info/top_level.txt