Metadata-Version: 1.1
Name: yake-github
Version: 0.4.0
Summary: Keyword extraction Python package
Home-page: https://pypi.python.org/pypi/yake
Author: UNKNOWN
Author-email: UNKNOWN
License: UNKNOWN
Keywords: yake
Platform: UNKNOWN
Classifier: Development Status :: 2 - Pre-Alpha
Classifier: Intended Audience :: Developers
Classifier: Natural Language :: English
Classifier: Programming Language :: Python :: 3
Classifier: Programming Language :: Python :: 3.3
Classifier: Programming Language :: Python :: 3.4
Classifier: Programming Language :: Python :: 3.5
